[
	{
		"inputs": [
			{
				"internalType": "uint256",
				"name": "_eventId",
				"type": "uint256"
			},
			{
				"internalType": "uint256",
				"name": "_numTicketsAvailable",
				"type": "uint256"
			},
			{
				"internalType": "string",
				"name": "_nameEvent",
				"type": "string"
			},
			{
				"internalType": "string",
				"name": "_locationEvent",
				"type": "string"
			},
			{
				"internalType": "uint256",
				"name": "_ticketPrice",
				"type": "uint256"
			}
		],
		"stateMutability": "nonpayable",
		"type": "constructor"
	},
	{
		"anonymous": false,
		"inputs": [
			{
				"indexed": false,
				"internalType": "address",
				"name": "buyer",
				"type": "address"
			},
			{
				"indexed": false,
				"internalType": "uint256",
				"name": "ticketID",
				"type": "uint256"
			}
		],
		"name": "BuyTicketEvent",
		"type": "event"
	},
	{
		"anonymous": false,
		"inputs": [
			{
				"indexed": true,
				"internalType": "address",
				"name": "previousOwner",
				"type": "address"
			},
			{
				"indexed": true,
				"internalType": "address",
				"name": "nerOwner",
				"type": "address"
			}
		],
		"name": "OwnershipTransferred",
		"type": "event"
	},
	{
		"inputs": [
			{
				"internalType": "address",
				"name": "buyer",
				"type": "address"
			},
			{
				"internalType": "string",
				"name": "_taxSeal",
				"type": "string"
			}
		],
		"name": "buyTicket",
		"outputs": [
			{
				"internalType": "bool",
				"name": "",
				"type": "bool"
			}
		],
		"stateMutability": "nonpayable",
		"type": "function"
	},
	{
		"inputs": [
			{
				"internalType": "address",
				"name": "buyer",
				"type": "address"
			},
			{
				"internalType": "string",
				"name": "_taxSeal",
				"type": "string"
			}
		],
		"name": "createTicket",
		"outputs": [
			{
				"internalType": "uint256",
				"name": "",
				"type": "uint256"
			}
		],
		"stateMutability": "nonpayable",
		"type": "function"
	},
	{
		"inputs": [
			{
				"internalType": "uint256",
				"name": "_eventID",
				"type": "uint256"
			}
		],
		"name": "deleteEvent",
		"outputs": [
			{
				"internalType": "bool",
				"name": "",
				"type": "bool"
			}
		],
		"stateMutability": "nonpayable",
		"type": "function"
	},
	{
		"inputs": [],
		"name": "getEventId",
		"outputs": [
			{
				"internalType": "uint256",
				"name": "",
				"type": "uint256"
			}
		],
		"stateMutability": "view",
		"type": "function"
	},
	{
		"inputs": [],
		"name": "getLocationEvent",
		"outputs": [
			{
				"internalType": "string",
				"name": "",
				"type": "string"
			}
		],
		"stateMutability": "view",
		"type": "function"
	},
	{
		"inputs": [],
		"name": "getNameEvent",
		"outputs": [
			{
				"internalType": "string",
				"name": "",
				"type": "string"
			}
		],
		"stateMutability": "view",
		"type": "function"
	},
	{
		"inputs": [],
		"name": "getNumTicketsAvailable",
		"outputs": [
			{
				"internalType": "uint256",
				"name": "",
				"type": "uint256"
			}
		],
		"stateMutability": "view",
		"type": "function"
	},
	{
		"inputs": [],
		"name": "getSoldTickets",
		"outputs": [
			{
				"internalType": "uint256",
				"name": "",
				"type": "uint256"
			}
		],
		"stateMutability": "view",
		"type": "function"
	},
	{
		"inputs": [
			{
				"internalType": "address",
				"name": "_ticketOwner",
				"type": "address"
			}
		],
		"name": "getTicket",
		"outputs": [
			{
				"components": [
					{
						"internalType": "string",
						"name": "taxSeal",
						"type": "string"
					},
					{
						"internalType": "uint256",
						"name": "ticketID",
						"type": "uint256"
					},
					{
						"internalType": "bool",
						"name": "valid",
						"type": "bool"
					}
				],
				"internalType": "struct Event.Tickets",
				"name": "",
				"type": "tuple"
			}
		],
		"stateMutability": "view",
		"type": "function"
	},
	{
		"inputs": [],
		"name": "getTicketPrice",
		"outputs": [
			{
				"internalType": "uint256",
				"name": "",
				"type": "uint256"
			}
		],
		"stateMutability": "view",
		"type": "function"
	},
	{
		"inputs": [],
		"name": "getTotalTickets",
		"outputs": [
			{
				"internalType": "uint256",
				"name": "",
				"type": "uint256"
			}
		],
		"stateMutability": "view",
		"type": "function"
	},
	{
		"inputs": [
			{
				"internalType": "address",
				"name": "owner",
				"type": "address"
			}
		],
		"name": "invalidation",
		"outputs": [
			{
				"internalType": "bool",
				"name": "",
				"type": "bool"
			}
		],
		"stateMutability": "nonpayable",
		"type": "function"
	},
	{
		"inputs": [],
		"name": "isDeleted",
		"outputs": [
			{
				"internalType": "bool",
				"name": "",
				"type": "bool"
			}
		],
		"stateMutability": "view",
		"type": "function"
	},
	{
		"inputs": [],
		"name": "owner",
		"outputs": [
			{
				"internalType": "address",
				"name": "",
				"type": "address"
			}
		],
		"stateMutability": "view",
		"type": "function"
	},
	{
		"inputs": [
			{
				"internalType": "string",
				"name": "_locationEvent",
				"type": "string"
			}
		],
		"name": "setLocationEvent",
		"outputs": [
			{
				"internalType": "bool",
				"name": "",
				"type": "bool"
			}
		],
		"stateMutability": "nonpayable",
		"type": "function"
	},
	{
		"inputs": [
			{
				"internalType": "string",
				"name": "_nameEvent",
				"type": "string"
			}
		],
		"name": "setNameEvent",
		"outputs": [
			{
				"internalType": "bool",
				"name": "",
				"type": "bool"
			}
		],
		"stateMutability": "nonpayable",
		"type": "function"
	},
	{
		"inputs": [
			{
				"internalType": "uint256",
				"name": "_numTicketsAvailable",
				"type": "uint256"
			}
		],
		"name": "setTicketAvailable",
		"outputs": [
			{
				"internalType": "bool",
				"name": "",
				"type": "bool"
			}
		],
		"stateMutability": "nonpayable",
		"type": "function"
	},
	{
		"inputs": [
			{
				"internalType": "uint256",
				"name": "_ticketPrice",
				"type": "uint256"
			}
		],
		"name": "setTicketPrice",
		"outputs": [
			{
				"internalType": "bool",
				"name": "",
				"type": "bool"
			}
		],
		"stateMutability": "nonpayable",
		"type": "function"
	},
	{
		"inputs": [
			{
				"internalType": "address",
				"name": "",
				"type": "address"
			}
		],
		"name": "ticket",
		"outputs": [
			{
				"internalType": "string",
				"name": "taxSeal",
				"type": "string"
			},
			{
				"internalType": "uint256",
				"name": "ticketID",
				"type": "uint256"
			},
			{
				"internalType": "bool",
				"name": "valid",
				"type": "bool"
			}
		],
		"stateMutability": "view",
		"type": "function"
	},
	{
		"inputs": [
			{
				"internalType": "address",
				"name": "newOwner",
				"type": "address"
			}
		],
		"name": "transferOwnership",
		"outputs": [
			{
				"internalType": "bool",
				"name": "",
				"type": "bool"
			}
		],
		"stateMutability": "nonpayable",
		"type": "function"
	}
]